sportydatagen/__init__.py
sportydatagen/activity.py
sportydatagen/cluster/__init__.py
sportydatagen/cluster/kmeans.py
sportydatagen/convert_to_csv.py
sportydatagen/csv_utils.py
sportydatagen/feature_extraction_utils.py
sportydatagen/filetype.py
sportydatagen/plot/__init__.py
sportydatagen/plot/correlation_heatmap.py
sportydatagen/plot/frequency_distribution.py
sportydatagen/plot/kmeans_scatter_plot.py
sportydatagen/plot/retention_value.py
sportydatagen/return_random_data.py
sportydatagen/saf_extract_features_to_csv.py
sportydatagen/sportfile_utils.py
sportydatagen/utils.py
sportydatagen-0.2.2.dist-info/LICENSE
sportydatagen-0.2.2.dist-info/WHEEL
sportydatagen-0.2.2.dist-info/METADATA
sportydatagen-0.2.2.dist-info/RECORD
