Metadata-Version: 2.1
Name: sportydatagen
Version: 0.2.2
Summary: Sports activity generator module
Home-page: https://gitlab.com/firefly-cpp/sportydatagen
License: MIT
Keywords: artificial sport trainer,computational intelligence,data mining,sport activities,tcx
Author: Rok Kukovec
Author-email: rok.kukovec1@student.um.si
Requires-Python: >=3.11,<4.0
Classifier: License :: OSI Approved :: MIT License
Classifier: Programming Language :: Python :: 3
Requires-Dist: niapy (>=2.0.5,<3.0.0)
Requires-Dist: numpy (>=1.24.2,<2.0.0)
Requires-Dist: pandas
Requires-Dist: scikit-learn (>=1.2.2,<2.0.0)
Requires-Dist: sport-activities-features (>=0.3.12,<0.4.0)
Project-URL: Repository, https://gitlab.com/firefly-cpp/sportydatagen
